meapp/__init__.py
meapp/debug.py
meapp/location_migrate.py
meapp/settings.py
meapp/urls.py
meapp/wsgi.py
meapp/aliyun/__init__.py
meapp/aliyun/sms.py
meapp/aliyun/views/__init__.py
meapp/aliyun/views/smsView.py
meapp/api/__init__.py
meapp/api/authentications.py
meapp/api/crawl.py
meapp/api/crossdomain.py
meapp/api/exception.py
meapp/api/response.py
meapp/api/view/__init__.py
meapp/api/view/authView.py
meapp/api/view/modelView.py
meapp/core/__init__.py
meapp/core/admin.py
meapp/core/apps.py
meapp/core/models.py
meapp/core/tests.py
meapp/core/views.py
meapp/core/api/__init__.py
meapp/core/api/serializer.py
meapp/core/api/urls.py
meapp/core/api/views.py
meapp/core/fields/ImageSetField.py
meapp/core/fields/__init__.py
meapp/core/fields/images.py
meapp/core/migrations/__init__.py
meapp/core/model/Images.py
meapp/core/model/__init__.py
meapp/location/__init__.py
meapp/location/admin.py
meapp/location/apps.py
meapp/location/models.py
meapp/location/tests.py
meapp/location/views.py
meapp/location/api/__init__.py
meapp/location/api/auth.py
meapp/location/api/serializer.py
meapp/location/api/urls.py
meapp/location/api/views.py
meapp/location/migrations/__init__.py
meapp/tools/__init__.py
meapp/tools/database_router.py
meapp/tools/datasrouter.py
meapp/tools/gencode.py
meapp-0.0.21.dist-info/METADATA
meapp-0.0.21.dist-info/WHEEL
meapp-0.0.21.dist-info/top_level.txt
meapp-0.0.21.dist-info/RECORD
